df2d/dataset.py
df2d/inference.py
df2d/model.py
df2d/parser.py
df2d/train.py
df2d/util.py
df2d-0.15.dist-info/METADATA
df2d-0.15.dist-info/WHEEL
df2d-0.15.dist-info/top_level.txt
df2d-0.15.dist-info/RECORD
