Metadata-Version: 2.1
Name: df2d
Version: 0.15
Summary: 2D pose estimation pipeline for tethered Drosophila.
Home-page: https://github.com/semihgunel/Drosophila2DPose
Author: Semih Gunel
Author-email: gunelsemih@gmail.com
License: UNKNOWN
Platform: UNKNOWN
